setup.py
googleearthplot/__init__.py
googleearthplot/googleearthplot.py
googleearthplot.egg-info/PKG-INFO
googleearthplot.egg-info/SOURCES.txt
googleearthplot.egg-info/dependency_links.txt
googleearthplot.egg-info/requires.txt
googleearthplot.egg-info/top_level.txt