Metadata-Version: 1.0
Name: googleearthplot
Version: 0.0.2
Summary: KML file generator for plotting on Google Earth
Home-page: https://github.com/AtsushiSakai/googleearthplot
Author: Atsushi Sakai
Author-email: asakai.amsl@gmail.com
License: MIT
Keywords: google earth plot kml
Platform: UNKNOWN
